awsaccountmgr/__init__.py
awsaccountmgr/account.py
awsaccountmgr/configparser.py
awsaccountmgr/organization.py
awsaccountmgr/sts.py
awsaccountmgr/vpc.py
awsaccountmgr-0.0.16.data/scripts/awsaccountmgr
awsaccountmgr-0.0.16.dist-info/LICENSE
awsaccountmgr-0.0.16.dist-info/METADATA
awsaccountmgr-0.0.16.dist-info/WHEEL
awsaccountmgr-0.0.16.dist-info/top_level.txt
awsaccountmgr-0.0.16.dist-info/RECORD
