Metadata-Version: 2.1
Name: awsaccountmgr
Version: 0.0.16
Summary: A command line tool for managing accounts within an AWS organization. Easy to integrate into AWS Deployment Framework
Home-page: https://github.com/thiezn/awsaccountmgr/
Author: Mathijs Mortimer
Author-email: mathijs@mortimer.nl
License: UNKNOWN
Keywords: AWS Accounts
Platform: UNKNOWN
Classifier: Programming Language :: Python :: 3.6
Classifier: Programming Language :: Python :: 3.7
Classifier: License :: OSI Approved :: MIT License
Classifier: Operating System :: OS Independent
License-File: LICENSE
Requires-Dist: boto3
Requires-Dist: pyyaml
